chemdata/__init__.py
chemdata/atom.json
chemdata/basic.py
chemdata/genelement.py
chemdata/nist.py
chemdata/nist_spectrum.json
chemdata-1.5.5.dist-info/LICENSE
chemdata-1.5.5.dist-info/METADATA
chemdata-1.5.5.dist-info/WHEEL
chemdata-1.5.5.dist-info/entry_points.txt
chemdata-1.5.5.dist-info/top_level.txt
chemdata-1.5.5.dist-info/RECORD
