Metadata-Version: 2.1
Name: chemdata
Version: 1.5.5
Summary: ('Basic Chemical Data, e.g. Chemical Elements, NIST Chemical Data',)
Home-page: https://github.com/atomse/chemdata
Author: Sky Zhang
Author-email: sky.atomse@gmail.com
Maintainer: Sky Zhang
Maintainer-email: sky.atomse@gmail.com
License: MIT License
Platform: Linux
Platform: Darwin
Classifier: Development Status :: 4 - Beta
Classifier: Operating System :: MacOS
Classifier: Operating System :: POSIX
Classifier: Intended Audience :: Science/Research
Classifier: License :: OSI Approved :: MIT License
Classifier: Programming Language :: Python
Classifier: Programming Language :: Python :: Implementation
Classifier: Programming Language :: Python :: 3
Classifier: Programming Language :: Python :: 3.5
Classifier: Programming Language :: Python :: 3.6
Classifier: Programming Language :: Python :: 3.7
Requires-Python: >=3
Provides-Extra: curate
Requires-Dist: graphviz ; extra == 'curate'
Provides-Extra: docs
Requires-Dist: sphinx ; extra == 'docs'
Requires-Dist: sphinxcontrib-programoutput ; extra == 'docs'
Requires-Dist: sphinx-rtd-theme ; extra == 'docs'
Requires-Dist: numpydoc ; extra == 'docs'
Provides-Extra: tests
Requires-Dist: pytest (>=4.0) ; extra == 'tests'
Requires-Dist: pytest-cov ; extra == 'tests'
